{
  "project_info": {
    "project_number": "795397625032",
    "project_id": "pocket-teacher-1b526",
    "storage_bucket": "pocket-teacher-1b526.appspot.com"
  },
  "client": [
    {
      "client_info": {
        "mobilesdk_app_id": "1:795397625032:android:f19589ee2e5119202d81fd",
        "android_client_info": {
          "package_name": "com.boroboro01.pocekt_teacher"
        }
      },
      "oauth_client": [],
      "api_key": [
        {
          "current_key": "AIzaSyCtBXxwucM9GAmphhMPMgHEF2AnKOKXa4k"
        }
      ],
      "services": {
        "appinvite_service": {
          "other_platform_oauth_client": []
        }
      }
    }
  ],
  "configuration_version": "1"
}